pkg_vers/__init__.py
pkg_vers/__main__.py
pkg_vers/package_manager.py
pkg_vers/utils.py
pkg_vers-0.1.2.dist-info/LICENSE.txt
pkg_vers-0.1.2.dist-info/METADATA
pkg_vers-0.1.2.dist-info/WHEEL
pkg_vers-0.1.2.dist-info/top_level.txt
pkg_vers-0.1.2.dist-info/RECORD
