Metadata-Version: 2.1
Name: pkg-vers
Version: 0.1.2
Summary: Easily extract and install packages necessary to run Python scripts and Jupyter notebooks.
Home-page: https://github.com/chuckfinca/pkg_vers
Author: Charles Feinn
Author-email: chuckfinca@gmail.com
Classifier: Programming Language :: Python :: 3
Classifier: License :: OSI Approved :: MIT License
Classifier: Operating System :: OS Independent
Requires-Python: >=3.8
License-File: LICENSE.txt
Requires-Dist: nbformat
Requires-Dist: stdlib-list
